Workbook

Sheet QA Summary
A1: DEV Changes QA Tracker
A2: One worksheet per QA module. Use each module’s Status dropdown, then return here for the live roll-up. Attach evidence or a defect link for every failure or blocker.
A3: Total Cases | B3: =SUM(B6:B19) -> 133 | C3: Passed | D3: =SUM(C6:C19) -> 50 | E3: Failed | F3: =SUM(D6:D19) -> 0 | G3: Blocked | H3: =SUM(E6:E19) -> 1 | I3: Complete % | J3: =IF(B3=0,0,(D3+F3+H3+SUM(H6:H19))/B3) -> 0.38345865 | K3: Build | L3: DEV - 2026-08-02
A5: Module | B5: Total | C5: Pass | D5: Fail | E5: Blocked | F5: In Progress | G5: Not Started | H5: N/A | I5: Complete % | J5: Owner | K5: Overall Status | L5: Notes
A6: Test Setup | B6: ='Test Setup'!B3 -> 10 | C6: ='Test Setup'!D3 -> 10 | D6: ='Test Setup'!F3 -> 0 | E6: ='Test Setup'!H3 -> 0 | F6: =COUNTIF('Test Setup'!G6:G15,"In Progress") -> 0 | G6: =COUNTIF('Test Setup'!G6:G15,"Not Started") -> 0 | H6: =COUNTIF('Test Setup'!G6:G15,"N/A") -> 0 | I6: =IF(B6=0,0,(C6+D6+E6+H6)/B6) -> 1 | K6: =IF(D6>0,"Fail",IF(E6>0,"Blocked",IF(F6>0,"In Progress",IF(C6+H6=B6,"Complete","Not Started")))) -> Complete
A7: Resource Onboarding | B7: ='Resource Onboarding'!B3 -> 8 | C7: ='Resource Onboarding'!D3 -> 8 | D7: ='Resource Onboarding'!F3 -> 0 | E7: ='Resource Onboarding'!H3 -> 0 | F7: =COUNTIF('Resource Onboarding'!G6:G13,"In Progress") -> 0 | G7: =COUNTIF('Resource Onboarding'!G6:G13,"Not Started") -> 0 | H7: =COUNTIF('Resource Onboarding'!G6:G13,"N/A") -> 0 | I7: =IF(B7=0,0,(C7+D7+E7+H7)/B7) -> 1 | K7: =IF(D7>0,"Fail",IF(E7>0,"Blocked",IF(F7>0,"In Progress",IF(C7+H7=B7,"Complete","Not Started")))) -> Complete
A8: Workspace Switching | B8: ='Workspace Switching'!B3 -> 6 | C8: ='Workspace Switching'!D3 -> 6 | D8: ='Workspace Switching'!F3 -> 0 | E8: ='Workspace Switching'!H3 -> 0 | F8: =COUNTIF('Workspace Switching'!G6:G11,"In Progress") -> 0 | G8: =COUNTIF('Workspace Switching'!G6:G11,"Not Started") -> 0 | H8: =COUNTIF('Workspace Switching'!G6:G11,"N/A") -> 0 | I8: =IF(B8=0,0,(C8+D8+E8+H8)/B8) -> 1 | K8: =IF(D8>0,"Fail",IF(E8>0,"Blocked",IF(F8>0,"In Progress",IF(C8+H8=B8,"Complete","Not Started")))) -> Complete
A9: Deployment | B9: =Deployment!B3 -> 10 | C9: =Deployment!D3 -> 10 | D9: =Deployment!F3 -> 0 | E9: =Deployment!H3 -> 0 | F9: =COUNTIF(Deployment!G6:G15,"In Progress") -> 0 | G9: =COUNTIF(Deployment!G6:G15,"Not Started") -> 0 | H9: =COUNTIF(Deployment!G6:G15,"N/A") -> 0 | I9: =IF(B9=0,0,(C9+D9+E9+H9)/B9) -> 1 | K9: =IF(D9>0,"Fail",IF(E9>0,"Blocked",IF(F9>0,"In Progress",IF(C9+H9=B9,"Complete","Not Started")))) -> Complete
A10: Inspection Completion | B10: ='Inspection Completion'!B3 -> 11 | C10: ='Inspection Completion'!D3 -> 9 | D10: ='Inspection Completion'!F3 -> 0 | E10: ='Inspection Completion'!H3 -> 1 | F10: =COUNTIF('Inspection Completion'!G6:G16,"In Progress") -> 1 | G10: =COUNTIF('Inspection Completion'!G6:G16,"Not Started") -> 0 | H10: =COUNTIF('Inspection Completion'!G6:G16,"N/A") -> 0 | I10: =IF(B10=0,0,(C10+D10+E10+H10)/B10) -> 0.90909091 | K10: =IF(D10>0,"Fail",IF(E10>0,"Blocked",IF(F10>0,"In Progress",IF(C10+H10=B10,"Complete","Not Started")))) -> Blocked
A11: Invoice Lifecycle | B11: ='Invoice Lifecycle'!B3 -> 14 | C11: ='Invoice Lifecycle'!D3 -> 7 | D11: ='Invoice Lifecycle'!F3 -> 0 | E11: ='Invoice Lifecycle'!H3 -> 0 | F11: =COUNTIF('Invoice Lifecycle'!G6:G19,"In Progress") -> 0 | G11: =COUNTIF('Invoice Lifecycle'!G6:G19,"Not Started") -> 7 | H11: =COUNTIF('Invoice Lifecycle'!G6:G19,"N/A") -> 0 | I11: =IF(B11=0,0,(C11+D11+E11+H11)/B11) -> 0.5 | K11: =IF(D11>0,"Fail",IF(E11>0,"Blocked",IF(F11>0,"In Progress",IF(C11+H11=B11,"Complete","Not Started")))) -> Not Started
A12: Gusto Payouts | B12: ='Gusto Payouts'!B3 -> 11 | C12: ='Gusto Payouts'!D3 -> 0 | D12: ='Gusto Payouts'!F3 -> 0 | E12: ='Gusto Payouts'!H3 -> 0 | F12: =COUNTIF('Gusto Payouts'!G6:G16,"In Progress") -> 0 | G12: =COUNTIF('Gusto Payouts'!G6:G16,"Not Started") -> 11 | H12: =COUNTIF('Gusto Payouts'!G6:G16,"N/A") -> 0 | I12: =IF(B12=0,0,(C12+D12+E12+H12)/B12) -> 0 | K12: =IF(D12>0,"Fail",IF(E12>0,"Blocked",IF(F12>0,"In Progress",IF(C12+H12=B12,"Complete","Not Started")))) -> Not Started
A13: Scheduler Regression | B13: ='Scheduler Regression'!B3 -> 10 | C13: ='Scheduler Regression'!D3 -> 0 | D13: ='Scheduler Regression'!F3 -> 0 | E13: ='Scheduler Regression'!H3 -> 0 | F13: =COUNTIF('Scheduler Regression'!G6:G15,"In Progress") -> 0 | G13: =COUNTIF('Scheduler Regression'!G6:G15,"Not Started") -> 10 | H13: =COUNTIF('Scheduler Regression'!G6:G15,"N/A") -> 0 | I13: =IF(B13=0,0,(C13+D13+E13+H13)/B13) -> 0 | K13: =IF(D13>0,"Fail",IF(E13>0,"Blocked",IF(F13>0,"In Progress",IF(C13+H13=B13,"Complete","Not Started")))) -> Not Started
A14: Employees Owners | B14: ='Employees Owners'!B3 -> 5 | C14: ='Employees Owners'!D3 -> 0 | D14: ='Employees Owners'!F3 -> 0 | E14: ='Employees Owners'!H3 -> 0 | F14: =COUNTIF('Employees Owners'!G6:G10,"In Progress") -> 0 | G14: =COUNTIF('Employees Owners'!G6:G10,"Not Started") -> 5 | H14: =COUNTIF('Employees Owners'!G6:G10,"N/A") -> 0 | I14: =IF(B14=0,0,(C14+D14+E14+H14)/B14) -> 0 | K14: =IF(D14>0,"Fail",IF(E14>0,"Blocked",IF(F14>0,"In Progress",IF(C14+H14=B14,"Complete","Not Started")))) -> Not Started
A15: Service Model | B15: ='Service Model'!B3 -> 17 | C15: ='Service Model'!D3 -> 0 | D15: ='Service Model'!F3 -> 0 | E15: ='Service Model'!H3 -> 0 | F15: =COUNTIF('Service Model'!G6:G22,"In Progress") -> 0 | G15: =COUNTIF('Service Model'!G6:G22,"Not Started") -> 17 | H15: =COUNTIF('Service Model'!G6:G22,"N/A") -> 0 | I15: =IF(B15=0,0,(C15+D15+E15+H15)/B15) -> 0 | K15: =IF(D15>0,"Fail",IF(E15>0,"Blocked",IF(F15>0,"In Progress",IF(C15+H15=B15,"Complete","Not Started")))) -> Not Started
A16: Help Center | B16: ='Help Center'!B3 -> 7 | C16: ='Help Center'!D3 -> 0 | D16: ='Help Center'!F3 -> 0 | E16: ='Help Center'!H3 -> 0 | F16: =COUNTIF('Help Center'!G6:G12,"In Progress") -> 0 | G16: =COUNTIF('Help Center'!G6:G12,"Not Started") -> 7 | H16: =COUNTIF('Help Center'!G6:G12,"N/A") -> 0 | I16: =IF(B16=0,0,(C16+D16+E16+H16)/B16) -> 0 | K16: =IF(D16>0,"Fail",IF(E16>0,"Blocked",IF(F16>0,"In Progress",IF(C16+H16=B16,"Complete","Not Started")))) -> Not Started
A17: Notifications Email | B17: ='Notifications Email'!B3 -> 6 | C17: ='Notifications Email'!D3 -> 0 | D17: ='Notifications Email'!F3 -> 0 | E17: ='Notifications Email'!H3 -> 0 | F17: =COUNTIF('Notifications Email'!G6:G11,"In Progress") -> 0 | G17: =COUNTIF('Notifications Email'!G6:G11,"Not Started") -> 6 | H17: =COUNTIF('Notifications Email'!G6:G11,"N/A") -> 0 | I17: =IF(B17=0,0,(C17+D17+E17+H17)/B17) -> 0 | K17: =IF(D17>0,"Fail",IF(E17>0,"Blocked",IF(F17>0,"In Progress",IF(C17+H17=B17,"Complete","Not Started")))) -> Not Started
A18: Cleanup Smoke | B18: ='Cleanup Smoke'!B3 -> 10 | C18: ='Cleanup Smoke'!D3 -> 0 | D18: ='Cleanup Smoke'!F3 -> 0 | E18: ='Cleanup Smoke'!H3 -> 0 | F18: =COUNTIF('Cleanup Smoke'!G6:G15,"In Progress") -> 0 | G18: =COUNTIF('Cleanup Smoke'!G6:G15,"Not Started") -> 10 | H18: =COUNTIF('Cleanup Smoke'!G6:G15,"N/A") -> 0 | I18: =IF(B18=0,0,(C18+D18+E18+H18)/B18) -> 0 | K18: =IF(D18>0,"Fail",IF(E18>0,"Blocked",IF(F18>0,"In Progress",IF(C18+H18=B18,"Complete","Not Started")))) -> Not Started
A19: Exit Criteria | B19: ='Exit Criteria'!B3 -> 8 | C19: ='Exit Criteria'!D3 -> 0 | D19: ='Exit Criteria'!F3 -> 0 | E19: ='Exit Criteria'!H3 -> 0 | F19: =COUNTIF('Exit Criteria'!G6:G13,"In Progress") -> 0 | G19: =COUNTIF('Exit Criteria'!G6:G13,"Not Started") -> 8 | H19: =COUNTIF('Exit Criteria'!G6:G13,"N/A") -> 0 | I19: =IF(B19=0,0,(C19+D19+E19+H19)/B19) -> 0 | K19: =IF(D19>0,"Fail",IF(E19>0,"Blocked",IF(F19>0,"In Progress",IF(C19+H19=B19,"Complete","Not Started")))) -> Not Started

Sheet Test Setup
A1: Test Setup QA | K1: ← QA Summary
A2: Prepare representative users, properties, billing data, and rates before executing workflow tests.
A3: Total | B3: =COUNTA(A6:A15) -> 10 | C3: Passed | D3: =COUNTIF(G6:G15,"Pass") -> 10 | E3: Failed | F3: =COUNTIF(G6:G15,"Fail") -> 0 | G3: Blocked | H3: =COUNTIF(G6:G15,"Blocked") -> 0 | I3: Completion | J3: =IF(B3=0,0,(COUNTIF(G6:G15,"Pass")+COUNTIF(G6:G15,"Fail")+COUNTIF(G6:G15,"Blocked")+COUNTIF(G6:G15,"N/A"))/B3) -> 1 | K3: Update Status in column G
A5: Test ID | B5: Priority | C5: Scenario | D5: Preconditions | E5: Test Steps | F5: Expected Outcome | G5: Status | H5: Tester | I5: Test Date | J5: Evidence / Defect Link | K5: Notes
A6: SET-01 | B6: P0 | C6: Platform administrator account | D6: DEV environment is reachable. | E6: Confirm an active platform administrator can sign in. | F6: Platform administration, Resources & Payables, service billing, and request-review areas are accessible. | G6: Pass | H6: Mitch | I6: 46237 | K6: account user is dev@afterlightinspections.com
A7: SET-02 | B7: P0 | C7: Organization administrator account | D7: A test organization exists. | E7: Confirm an organization administrator can sign in to the organization workspace. | F7: Organization administration and service-model request features are accessible without platform-only permissions. | G7: Pass | H7: mitch | I7: 46237 | K7: account user is mitchfurrier@gmail.com
A8: SET-03 | B8: P0 | C8: Assigned property manager | D8: Property A belongs to the test organization. | E8: Assign a property manager to Property A and confirm sign-in. | F8: The manager can access Property A review flows and cannot access unassigned properties. | G8: Pass | H8: Mitch | I8: 46237 | K8: account user is highspeedmitch@gmail.com
A9: SET-04 | B9: P0 | C9: Dual-workspace submitter | D9: An existing organization submitter email is available. | E9: Record the submitter identity for later contractor linking. | F9: The same identity can be used to verify organization/resource workspace switching without duplication. | G9: Pass | H9: Mitch | I9: 46237 | K9: account user is skylinemitch@outlook.com
A10: SET-05 | B10: P0 | C10: New contractor email | D10: Use an email that has never signed in to DEV. | E10: Record the address for contractor invitation testing. | F10: The address is ready for a resource-only onboarding path. | G10: Pass | H10: Mitch | I10: 46237 | K10: account user is Al1099Dev@yahoo.com
A11: SET-06 | B11: P1 | C11: Employee or owner resource | D11: An employee or owner relationship can be created. | E11: Create or identify an active employee/owner resource. | F11: The resource is available for non-contractor scheduling and payable-exclusion tests. | G11: Pass | H11: Mitch | I11: 46237 | K11: AlEmployee1@proton.me
A12: SET-07 | B12: P1 | C12: Ordinary organization user | D12: A non-admin, non-manager organization account exists. | E12: Confirm the user can sign in. | F12: The account is ready for permission-denial checks. | G12: Pass | H12: Mitch | I12: 46237 | K12: gunguymitch@gmail.com
A13: SET-08 | B13: P0 | C13: Property A billing configuration | D13: Property A is managed or hybrid and eligible for deployment. | E13: Set a billing code, customer amount, assigned property manager, and accounts-payable email. | F13: Property A is fully configured for assignment, invoice, review, and AP delivery tests. | G13: Pass | H13: Mitch | I13: 46237 | K13: Property is Winterhaven Square
A14: SET-09 | B14: P1 | C14: Property B exclusion case | D14: Property B is in the same test organization. | E14: Leave the contractor undeployed to Property B. | F14: Property B can prove property-scoped resource eligibility. | G14: Pass | H14: Mitch | I14: 46237
A15: SET-10 | B15: P0 | C15: Rate fixtures | D15: A contractor profile is available. | E15: Set the contractor default to $75 and prepare a Property A override of $90. | F15: Tests can verify rate overrides and immutable assignment snapshots. | G15: Pass | H15: Mitch | I15: 46237 | K15: rate is set to $75 on al1099dev

Sheet Resource Onboarding
A1: Resource Onboarding QA | K1: ← QA Summary
A2: Validate contractor linking, invitations, eligibility gates, activation, and suspension behavior.
A3: Total | B3: =COUNTA(A6:A13) -> 8 | C3: Passed | D3: =COUNTIF(G6:G13,"Pass") -> 8 | E3: Failed | F3: =COUNTIF(G6:G13,"Fail") -> 0 | G3: Blocked | H3: =COUNTIF(G6:G13,"Blocked") -> 0 | I3: Completion | J3: =IF(B3=0,0,(COUNTIF(G6:G13,"Pass")+COUNTIF(G6:G13,"Fail")+COUNTIF(G6:G13,"Blocked")+COUNTIF(G6:G13,"N/A"))/B3) -> 1 | K3: Update Status in column G
A5: Test ID | B5: Priority | C5: Scenario | D5: Preconditions | E5: Test Steps | F5: Expected Outcome | G5: Status | H5: Tester | I5: Test Date | J5: Evidence / Defect Link | K5: Notes
A6: ONB-01 | B6: P0 | C6: Open Resources & Payables | D6: Signed in as a platform administrator. | E6: Open Resources & Payables. | F6: Profiles, deployments, earnings, and payout batches are visible and load without errors. | G6: Pass | H6: Mitch | I6: 46237 | K6: account is dev@afterlightinspections.com
A7: ONB-02 | B7: P0 | C7: Link an existing submitter | D7: Existing organization submitter is not yet a contractor. | E7: Add the submitter email as a contractor. | F7: The existing identity is linked; no duplicate user or unnecessary invitation is created. | G7: Pass | H7: Mitch | I7: 46237 | K7: account is skylinemitch@outlook.com
A8: ONB-03 | B8: P0 | C8: Reject duplicate contractor email | D8: The submitter is already linked as a contractor. | E8: Attempt to add the same email again. | F8: The duplicate is rejected with a clear message and no second profile is created. | G8: Pass | H8: Mitch | I8: 46237 | K8: duplicate account was attempted on al1099dev@yahoo.com and failed succesfully
A9: ONB-04 | B9: P0 | C9: Invite a new contractor | D9: Unused email is available. | E9: Add the new email as a contractor. | F9: An invitation is created and the account begins as resource-only unless separately linked to an organization. | G9: Pass | H9: Mitch | I9: 46237 | K9: al1099dev@yahoo.com,
A10: ONB-05 | B10: P0 | C10: Block premature activation | D10: Contractor onboarding is incomplete in Gusto. | E10: Attempt to mark the contractor Active. | F10: Activation is refused and the UI identifies the missing Gusto prerequisite. | G10: Pass | H10: Mitch | I10: 46237 | K10: Confirmed system failure notification that Gusto onboarding must be complete before resource ativation
A11: ONB-06 | B11: P0 | C11: Complete Gusto onboarding and activate | D11: Contractor profile exists and is inactive. | E11: Mark Gusto onboarding Completed, then mark the profile Active. | F11: The contractor becomes active and previously entered profile/rate values remain intact. | G11: Pass | H11: Mitch | I11: 46237 | K11: confirmed success
A12: ONB-07 | B12: P1 | C12: Reject ineligible identity link | D12: Use an inactive, admin-only, or property-manager-only account. | E12: Attempt to link the account as a contractor. | F12: The link is rejected without changing either identity or role memberships. | G12: Pass | H12: Mitch | I12: 46237 | K12: Confirmed inelligible. May need to update error to state that they are inelligible due to already existing as role with elevated permissions
A13: ONB-08 | B13: P0 | C13: Suspend a resource profile | D13: A dual-workspace contractor is active. | E13: Suspend the profile, then reauthenticate. | F13: Resource entitlement is removed on the next authentication while historical assignments and earnings remain available to authorized admins. | G13: Pass | H13: Mitch | I13: 46237

Sheet Workspace Switching
A1: Workspace Switching QA | K1: ← QA Summary
A2: Verify identity-safe navigation between organization and resource workspaces.
A3: Total | B3: =COUNTA(A6:A11) -> 6 | C3: Passed | D3: =COUNTIF(G6:G11,"Pass") -> 6 | E3: Failed | F3: =COUNTIF(G6:G11,"Fail") -> 0 | G3: Blocked | H3: =COUNTIF(G6:G11,"Blocked") -> 0 | I3: Completion | J3: =IF(B3=0,0,(COUNTIF(G6:G11,"Pass")+COUNTIF(G6:G11,"Fail")+COUNTIF(G6:G11,"Blocked")+COUNTIF(G6:G11,"N/A"))/B3) -> 1 | K3: Update Status in column G
A5: Test ID | B5: Priority | C5: Scenario | D5: Preconditions | E5: Test Steps | F5: Expected Outcome | G5: Status | H5: Tester | I5: Test Date | J5: Evidence / Defect Link | K5: Notes
A6: WRK-01 | B6: P0 | C6: Expose resource workspace after reauthentication | D6: Existing submitter has been linked as an active contractor. | E6: Sign out and sign back in. | F6: The Resource Portal option appears for the same identity. | G6: Pass | H6: Mitch | I6: 46237 | K6: Tested with Skylinemitch@Outlook.com
A7: WRK-02 | B7: P0 | C7: Switch organization to resource | D7: Dual-workspace account is in the organization workspace. | E7: Use the workspace switcher to open Resource Portal. | F7: The portal opens under the same identity with only resource-authorized data. | G7: Pass | H7: Mitch | I7: 46237 | K7: Tested with Skylinemitch@Outlook.com
A8: WRK-03 | B8: P0 | C8: Switch resource to organization | D8: Dual-workspace account is in Resource Portal. | E8: Switch back to the organization workspace. | F8: The correct organization role and access are restored. | G8: Pass | H8: Mitch | I8: 46237 | K8: Tested with Skylinemitch@Outlook.com
A9: WRK-04 | B9: P1 | C9: Hide switcher for organization-only user | D9: User has no resource profile. | E9: Sign in and inspect global navigation. | F9: No Resource Portal switch option is shown. | G9: Pass | H9: Mitch | I9: 46237
A10: WRK-05 | B10: P0 | C10: Restrict resource-only account | D10: New contractor has no organization membership. | E10: Attempt to enter an organization workspace directly. | F10: Access is denied or redirected safely to Resource Portal. | G10: Pass | H10: Mitch | I10: 46237
A11: WRK-06 | B11: P0 | C11: Safe fallback after suspension | D11: A dual-workspace resource profile has been suspended. | E11: Reauthenticate and attempt to open Resource Portal. | F11: Resource access is denied and the user safely falls back to their authorized organization workspace. | G11: Pass | H11: Mitch | I11: 46237

Sheet Deployment
A1: Deployment QA | K1: ← QA Summary
A2: Validate resource deployment, property eligibility, scheduling, assignment visibility, and compensation snapshots.
A3: Total | B3: =COUNTA(A6:A15) -> 10 | C3: Passed | D3: =COUNTIF(G6:G15,"Pass") -> 10 | E3: Failed | F3: =COUNTIF(G6:G15,"Fail") -> 0 | G3: Blocked | H3: =COUNTIF(G6:G15,"Blocked") -> 0 | I3: Completion | J3: =IF(B3=0,0,(COUNTIF(G6:G15,"Pass")+COUNTIF(G6:G15,"Fail")+COUNTIF(G6:G15,"Blocked")+COUNTIF(G6:G15,"N/A"))/B3) -> 1 | K3: Update Status in column G
A5: Test ID | B5: Priority | C5: Scenario | D5: Preconditions | E5: Test Steps | F5: Expected Outcome | G5: Status | H5: Tester | I5: Test Date | J5: Evidence / Defect Link | K5: Notes
A6: DEP-01 | B6: P0 | C6: Deploy contractor to Property A | D6: Contractor is active; Property A is managed or hybrid. | E6: Create an active deployment scoped to Property A. | F6: The deployment saves and shows the correct organization, property, dates, and active status. | G6: Pass | H6: Mitch | I6: 46237 | K6: AL 1099 Resource
A7: DEP-02 | B7: P0 | C7: Apply property rate override | D7: Contractor default is $75. | E7: Set the Property A override to $90. | F7: The deployment shows $90 while the contractor default remains $75. | G7: Pass | H7: Mitch | I7: 46237 | K7: AL 1099 Resource
A8: DEP-03 | B8: P0 | C8: Show deployed contractor in scheduler | D8: Active deployment exists for Property A. | E8: Open Property A scheduling and choose the Afterlight contractor source. | F8: The contractor appears as an eligible resource. | G8: Pass | H8: Mitch | I8: 46237
A9: DEP-04 | B9: P0 | C9: Exclude contractor from Property B | D9: Contractor is not deployed to Property B. | E9: Open Property B scheduling. | F9: The contractor does not appear and cannot be assigned by a crafted request. | G9: Pass | H9: Mitch | I9: 46237
A10: DEP-05 | B10: P0 | C10: Pause or end deployment | D10: A deployment is active. | E10: Pause or end it, then create a future assignment. | F10: The resource is unavailable for future scheduling outside the active deployment window. | G10: Pass | H10: Mitch | I10: 46237
A11: DEP-06 | B11: P1 | C11: Respect resource unavailability | D11: Resource is deployed but marked unavailable for the target date. | E11: Attempt to schedule the resource. | F11: The resource is excluded or the assignment is rejected with an availability message. | G11: Pass | H11: Mitch | I11: 46237
A12: DEP-07 | B12: P0 | C12: Create single-day assignment | D12: Resource is eligible for Property A. | E12: Create an assignment with a start date and no end date. | F12: The assignment saves and is displayed as a single-day assignment. | G12: Pass | H12: Mitch | I12: 46237
A13: DEP-08 | B13: P0 | C13: Display assignment card details | D13: Assignment exists for the contractor. | E13: Open Resource Portal and inspect the card. | F13: Organization, property, dates, instructions, and $90 compensation are displayed correctly. | G13: Pass | H13: Mitch | I13: 46237
A14: DEP-09 | B14: P0 | C14: Preserve assignment compensation snapshot | D14: An assignment was created at $90. | E14: Change the contractor/deployment rate after assignment creation. | F14: The existing assignment still shows $90; only later assignments use the new rate. | G14: Pass | H14: Mitch | I14: 46237
A15: DEP-10 | B15: P1 | C15: Enforce deployment date boundaries | D15: Deployment has explicit start and end dates. | E15: Try assignments immediately before, within, and after the range. | F15: Only dates within the active range are accepted. | G15: Pass | H15: Mitch | I15: 46237

Sheet Inspection Completion
A1: Inspection Completion QA | K1: ← QA Summary
A2: Exercise contractor inspection execution, security, retry safety, PDF persistence, and earning creation.
A3: Total | B3: =COUNTA(A6:A16) -> 11 | C3: Passed | D3: =COUNTIF(G6:G16,"Pass") -> 9 | E3: Failed | F3: =COUNTIF(G6:G16,"Fail") -> 0 | G3: Blocked | H3: =COUNTIF(G6:G16,"Blocked") -> 1 | I3: Completion | J3: =IF(B3=0,0,(COUNTIF(G6:G16,"Pass")+COUNTIF(G6:G16,"Fail")+COUNTIF(G6:G16,"Blocked")+COUNTIF(G6:G16,"N/A"))/B3) -> 0.90909091 | K3: Update Status in column G
A5: Test ID | B5: Priority | C5: Scenario | D5: Preconditions | E5: Test Steps | F5: Expected Outcome | G5: Status | H5: Tester | I5: Test Date | J5: Evidence / Defect Link | K5: Notes
A6: INS-01 | B6: P0 | C6: Start inspection from assignment | D6: An active contractor assignment is visible. | E6: Open the assignment card and start the inspection. | F6: The correct checklist loads with the expected assignment and property identity. | G6: Pass | H6: Mitch | I6: 46237 | K6: account tested in gunguymitch@gmail.com
A7: INS-02 | B7: P1 | C7: Display assignment instructions | D7: Assignment includes custom instructions. | E7: Open the inspection experience. | F7: Instructions are complete, readable, and associated with the correct assignment. | G7: Pass | H7: Mitch | I7: 46237 | K7: account tested in gunguymitch@gmail.com
A8: INS-03 | B8: P0 | C8: Block missing required field | D8: Inspection checklist is open. | E8: Leave a required field blank and submit. | F8: Submission is blocked and the missing field is clearly identified. | G8: Pass | H8: Mitch | I8: 46237 | K8: account tested in gunguymitch@gmail.com
A9: INS-04 | B9: P0 | C9: Upload photos once | D9: Valid photos are available. | E9: Attach photos and submit while observing progress/retry states. | F9: Uploads use the secure path, progress is visible, and no duplicate asset is created. | G9: Pass | H9: Mitch | I9: 46237 | K9: account tested in gunguymitch@gmail.com
A10: INS-05 | B10: P0 | C10: Complete assigned inspection | D10: All required data is valid. | E10: Submit the inspection. | F10: The inspection reaches Complete and a completion confirmation is shown. | G10: Pass | H10: Mitch | I10: 46237 | K10: account tested in gunguymitch@gmail.com
A11: INS-06 | B11: P0 | C11: Remove completed assignment from active portal | D11: Inspection completed successfully. | E11: Return to or refresh Resource Portal. | F11: The completed assignment is no longer listed as active work. | G11: Pass | H11: Mitch | I11: 46237 | K11: account tested in gunguymitch@gmail.com
A12: INS-07 | B12: P0 | C12: Prevent duplicate completion on retry | D12: A completion response is delayed or retried. | E12: Refresh/retry the completion request. | F12: Only one inspection, PDF, invoice, and earning are associated with the assignment. | G12: Blocked
A13: INS-08 | B13: P0 | C13: Reject property or URL tampering | D13: Resource has an assignment only for Property A. | E13: Alter a property/assignment identifier in the URL or request. | F13: The request is denied and no unauthorized property data is exposed. | G13: Pass | H13: Mitch | I13: 46237 | K13: account tested in gunguymitch@gmail.com
A14: INS-09 | B14: P0 | C14: Persist completion when SES fails | D14: Email delivery is configured to fail. | E14: Complete an otherwise valid inspection. | F14: Inspection and PDF persist; delivery failure is recorded and no duplicate is produced. | G14: In Progress | H14: Mitch | I14: 46237
A15: INS-10 | B15: P0 | C15: Create one contractor earning | D15: Contractor assignment has $90 snapshot. | E15: Inspect Resources & Payables after completion. | F15: Exactly one $90 earning exists in Pending Approval for the contractor. | G15: Pass | H15: Mitch | I15: 46237 | K15: al1099dev@yahoo.com
A16: INS-11 | B16: P0 | C16: Exclude employee/owner from payable creation | D16: Employee/owner assignment is available. | E16: Complete the same workflow as an employee/owner. | F16: The inspection completes but no contractor earning is created. | G16: Pass | H16: Mitch | I16: 46237 | K16: skylinemitch@outlook.com

Sheet Invoice Lifecycle
A1: Invoice Lifecycle QA | K1: ← QA Summary
A2: Validate customer invoice preparation, review, revisions, AP delivery, and independent payment state.
A3: Total | B3: =COUNTA(A6:A19) -> 14 | C3: Passed | D3: =COUNTIF(G6:G19,"Pass") -> 7 | E3: Failed | F3: =COUNTIF(G6:G19,"Fail") -> 0 | G3: Blocked | H3: =COUNTIF(G6:G19,"Blocked") -> 0 | I3: Completion | J3: =IF(B3=0,0,(COUNTIF(G6:G19,"Pass")+COUNTIF(G6:G19,"Fail")+COUNTIF(G6:G19,"Blocked")+COUNTIF(G6:G19,"N/A"))/B3) -> 0.5 | K3: Update Status in column G
A5: Test ID | B5: Priority | C5: Scenario | D5: Preconditions | E5: Test Steps | F5: Expected Outcome | G5: Status | H5: Tester | I5: Test Date | J5: Evidence / Defect Link | K5: Notes
A6: INV-01 | B6: P0 | C6: Auto-create customer invoice | D6: Afterlight commercial inspection completes with billing fully configured. | E6: Complete the inspection and open service billing. | F6: One platform-owned invoice and PDF are created in Awaiting Review. | G6: Pass | H6: Mitch | K6: Al1099dev@yahoo.com
A7: INV-02 | B7: P0 | C7: Verify invoice PDF fields | D7: Invoice PDF exists. | E7: Open the PDF and compare it with property, service, and performer data. | F7: Billing code, amount, property, service details, and performer are correct; Afterlight is the invoice owner. | G7: Pass | H7: Mitch | K7: Al1099dev@yahoo.com
A8: INV-03 | B8: P0 | C8: Deny billing access to resource | D8: Signed in as the contractor performer. | E8: Attempt to open Billing or the invoice directly. | F8: Billing access is denied without exposing customer amounts. | G8: Pass | H8: Mitch | K8: al1099dev@yahoo.com
A9: INV-04 | B9: P0 | C9: Allow only assigned manager review | D9: Assigned and unassigned property-manager accounts exist. | E9: Open the invoice as each manager. | F9: Assigned manager can review; unassigned manager is denied. | G9: Pass | H9: Mitch | K9: Al1099dev@yahoo.com
A10: INV-05 | B10: P1 | C10: Require decline reason | D10: Invoice is Awaiting Review. | E10: Choose Decline without a reason. | F10: The action is rejected and invoice status does not change. | G10: Pass | H10: Mitch | K10: Invoice BLK01-1785815140114
A11: INV-06 | B11: P0 | C11: Decline with reason | D11: Invoice is Awaiting Review. | E11: Decline and enter a reason. | F11: Status becomes Needs Revision and the reason appears in Platform Service Billing. | G11: Pass | H11: Mitch | K11: Invoice BLK01-1785815140114
A12: INV-07 | B12: P0 | C12: Invalidate stale PDF after amount change | D12: Invoice needs revision. | E12: Change the customer amount as a platform administrator. | F12: The prior PDF is invalidated and cannot be resent as the current invoice. | G12: Pass | H12: Mitch
A13: INV-08 | B13: P0 | C13: Regenerate and resend revision | D13: Invoice amount has changed. | E13: Regenerate the PDF and resend for review. | F13: The new amount and PDF are used and status returns to Awaiting Review. | G13: Not Started
A14: INV-09 | B14: P0 | C14: Approve and send to AP | D14: Invoice is valid and awaiting assigned-manager review. | E14: Approve and send it to accounts payable. | F14: Status becomes Sent to AP and the expected attachment is delivered. | G14: Not Started
A15: INV-10 | B15: P0 | C15: Handle invalid AP address safely | D15: Set an invalid AP email. | E15: Attempt AP delivery. | F15: Status records AP Delivery Failed while the invoice and inspection remain intact. | G15: Not Started
A16: INV-11 | B16: P0 | C16: Retry AP delivery without duplication | D16: An AP delivery has failed. | E16: Correct the email and retry. | F16: Delivery succeeds using the same invoice; no duplicate invoice is created. | G16: Not Started
A17: INV-12 | B17: P0 | C17: Keep payout and invoice payment independent | D17: Invoice and contractor earning both exist. | E17: Mark the contractor payout paid. | F17: Customer invoice remains unpaid and unchanged. | G17: Not Started
A18: INV-13 | B18: P0 | C18: Mark customer invoice paid independently | D18: Customer invoice is sent or payable. | E18: Mark the customer invoice paid. | F18: Only customer invoice state changes; contractor earning/batch state is unchanged. | G18: Not Started
A19: INV-14 | B19: P1 | C19: Surface missing billing configuration | D19: Remove amount, billing code, manager, or AP data in separate runs. | E19: Complete an inspection for each missing field. | F19: Submission succeeds but the invoice shows a visible draft/preparation exception identifying the missing configuration. | G19: Not Started

Sheet Gusto Payouts
A1: Gusto Payouts QA | K1: ← QA Summary
A2: Validate earning approval, voids, payout batching, submission, payment, and onboarding safeguards.
A3: Total | B3: =COUNTA(A6:A16) -> 11 | C3: Passed | D3: =COUNTIF(G6:G16,"Pass") -> 0 | E3: Failed | F3: =COUNTIF(G6:G16,"Fail") -> 0 | G3: Blocked | H3: =COUNTIF(G6:G16,"Blocked") -> 0 | I3: Completion | J3: =IF(B3=0,0,(COUNTIF(G6:G16,"Pass")+COUNTIF(G6:G16,"Fail")+COUNTIF(G6:G16,"Blocked")+COUNTIF(G6:G16,"N/A"))/B3) -> 0 | K3: Update Status in column G
A5: Test ID | B5: Priority | C5: Scenario | D5: Preconditions | E5: Test Steps | F5: Expected Outcome | G5: Status | H5: Tester | I5: Test Date | J5: Evidence / Defect Link | K5: Notes
A6: PAY-01 | B6: P0 | C6: Approve pending earning | D6: A contractor earning is Pending Approval. | E6: Approve the earning. | F6: Status becomes Approved and it becomes eligible for batching. | G6: Not Started
A7: PAY-02 | B7: P1 | C7: Void eligible earning with reason | D7: Use a Pending Approval or Approved earning. | E7: Void the earning and provide a reason. | F7: Status becomes Void and the reason is retained in audit history. | G7: Not Started
A8: PAY-03 | B8: P0 | C8: Create batch from approved earnings | D8: Multiple Approved earnings are selected. | E8: Create a Gusto batch. | F8: Batch count and total match the selected eligible earnings. | G8: Not Started
A9: PAY-04 | B9: P0 | C9: Exclude unapproved earning from batch | D9: At least one earning is not Approved. | E9: Attempt to include it in a batch. | F9: The earning is refused or excluded and the batch totals remain correct. | G9: Not Started
A10: PAY-05 | B10: P0 | C10: Generate dated grouped payout batch | D10: Approved earnings for one or more contractors exist. | E10: Create the batch with a check date. | F10: A date-stamped batch number is created, earnings are grouped by contractor, and state becomes payout_pending. | G10: Not Started
A11: PAY-06 | B11: P0 | C11: Protect batched earning from void | D11: Earning belongs to an active payout batch. | E11: Attempt to void it. | F11: The action is refused so batch totals cannot silently change. | G11: Not Started
A12: PAY-07 | B12: P0 | C12: Record Gusto submission reference | D12: Batch is Ready for submission. | E12: Record the external submission reference. | F12: Batch becomes Submitted and the reference is retained. | G12: Not Started
A13: PAY-08 | B13: P1 | C13: Cancel Mark Paid confirmation | D13: A submitted batch is open. | E13: Start Mark Paid, then cancel. | F13: No batch or earning status changes. | G13: Not Started
A14: PAY-09 | B14: P0 | C14: Confirm Mark Paid | D14: A submitted batch is open. | E14: Confirm Mark Paid. | F14: Batch and all included earnings become Paid exactly once. | G14: Not Started
A15: PAY-10 | B15: P0 | C15: Reject invalid contractor payout identity | D15: Contractor has missing/mismatched email or incomplete onboarding. | E15: Attempt to create/submit a batch containing the earning. | F15: The batch action is refused with an actionable validation message. | G15: Not Started
A16: PAY-11 | B16: P0 | C16: Keep contractor amount independent | D16: Customer invoice amount differs from contractor compensation. | E16: Compare earning, batch, and invoice values. | F16: Payout uses the assignment compensation snapshot, not the customer invoice amount. | G16: Not Started

Sheet Scheduler Regression
A1: Scheduler Regression QA | K1: ← QA Summary
A2: Protect mobile layout, date handling, conflict rules, completed-assignment behavior, and role-based resource sources.
A3: Total | B3: =COUNTA(A6:A15) -> 10 | C3: Passed | D3: =COUNTIF(G6:G15,"Pass") -> 0 | E3: Failed | F3: =COUNTIF(G6:G15,"Fail") -> 0 | G3: Blocked | H3: =COUNTIF(G6:G15,"Blocked") -> 0 | I3: Completion | J3: =IF(B3=0,0,(COUNTIF(G6:G15,"Pass")+COUNTIF(G6:G15,"Fail")+COUNTIF(G6:G15,"Blocked")+COUNTIF(G6:G15,"N/A"))/B3) -> 0 | K3: Update Status in column G
A5: Test ID | B5: Priority | C5: Scenario | D5: Preconditions | E5: Test Steps | F5: Expected Outcome | G5: Status | H5: Tester | I5: Test Date | J5: Evidence / Defect Link | K5: Notes
A6: SCH-01 | B6: P1 | C6: Use scheduler at 390px | D6: Browser dev tools or a 390px device is available. | E6: Open and exercise the scheduler at 390px width. | F6: Controls remain usable and the page has no unintended horizontal scrolling. | G6: Not Started
A7: SCH-02 | B7: P0 | C7: Correct invalid end date | D7: Scheduler create/edit form is open. | E7: Set a start date after the current end date. | F7: The invalid end date is cleared or corrected and cannot be saved incorrectly. | G7: Not Started
A8: SCH-03 | B8: P0 | C8: Create multi-day assignment | D8: Eligible resource and property exist. | E8: Set valid start and end dates and save. | F8: The exact date range is persisted and displayed. | G8: Not Started
A9: SCH-04 | B9: P0 | C9: Edit single-day assignment | D9: A single-day assignment exists. | E9: Open edit mode. | F9: Start date is populated and end date remains blank. | G9: Not Started
A10: SCH-05 | B10: P0 | C10: Drag assignment to new date | D10: Draggable scheduled assignment exists. | E10: Drag it to a valid date and refresh. | F10: Persisted dates match the new calendar position. | G10: Not Started
A11: SCH-06 | B11: P0 | C11: Reject schedule conflict | D11: Resource already has a conflicting active assignment. | E11: Attempt an overlapping assignment. | F11: The conflict is rejected without modifying the existing assignment. | G11: Not Started
A12: SCH-07 | B12: P0 | C12: Allow reuse after completion | D12: Same resource/property/date combination was completed. | E12: Schedule that combination again. | F12: The new assignment succeeds and no obsolete uniqueness constraint blocks it. | G12: Not Started
A13: SCH-08 | B13: P0 | C13: Protect completed assignment | D13: A completed assignment exists. | E13: Attempt to edit or delete it. | F13: The action is refused or safely constrained so completed inspection history is preserved. | G13: Not Started
A14: SCH-09 | B14: P0 | C14: Enforce manager property scope | D14: Property manager is not assigned to Property B. | E14: Attempt to schedule Property B. | F14: Property B is hidden or the write is rejected. | G14: Not Started
A15: SCH-10 | B15: P1 | C15: Filter fulfillment sources | D15: Employee/owner and contractor resources exist. | E15: Switch between staff and contractor fulfillment sources. | F15: Employee/owner appears only under the staff source and contractor only under the contractor source. | G15: Not Started

Sheet Employees Owners
A1: Employees Owners QA | K1: ← QA Summary
A2: Verify non-contractor resources can be deployed and scheduled without creating payables.
A3: Total | B3: =COUNTA(A6:A10) -> 5 | C3: Passed | D3: =COUNTIF(G6:G10,"Pass") -> 0 | E3: Failed | F3: =COUNTIF(G6:G10,"Fail") -> 0 | G3: Blocked | H3: =COUNTIF(G6:G10,"Blocked") -> 0 | I3: Completion | J3: =IF(B3=0,0,(COUNTIF(G6:G10,"Pass")+COUNTIF(G6:G10,"Fail")+COUNTIF(G6:G10,"Blocked")+COUNTIF(G6:G10,"N/A"))/B3) -> 0 | K3: Update Status in column G
A5: Test ID | B5: Priority | C5: Scenario | D5: Preconditions | E5: Test Steps | F5: Expected Outcome | G5: Status | H5: Tester | I5: Test Date | J5: Evidence / Defect Link | K5: Notes
A6: PPL-01 | B6: P0 | C6: Create employee or owner resource | D6: Platform administrator is signed in. | E6: Add an employee/owner resource without Gusto data or a contractor rate. | F6: The relationship saves without requiring contractor payout fields. | G6: Not Started
A7: PPL-02 | B7: P0 | C7: Deploy and schedule staff | D7: Employee/owner resource is active. | E7: Deploy and schedule through the Afterlight staff source. | F7: The resource appears in the correct source and can be assigned to eligible property/dates. | G7: Not Started
A8: PPL-03 | B8: P0 | C8: Complete staff inspection without payable | D8: Employee/owner assignment exists. | E8: Complete the inspection. | F8: Customer invoicing may proceed, but no contractor earning is created. | G8: Not Started
A9: PPL-04 | B9: P1 | C9: Show relationship instead of earnings | D9: Employee/owner signs into the resource experience. | E9: Inspect portal summary/details. | F9: The employment/owner relationship is shown without contractor earning amounts. | G9: Not Started
A10: PPL-05 | B10: P1 | C10: Hide contractor payout guidance | D10: Employee/owner is signed in. | E10: Open contextual help. | F10: Contractor earnings/Gusto guidance is hidden or replaced with appropriate non-payable guidance. | G10: Not Started

Sheet Service Model
A1: Service Model QA | K1: ← QA Summary
A2: Validate governed service-model changes, review decisions, notifications, versioning, and future-only effects.
A3: Total | B3: =COUNTA(A6:A22) -> 17 | C3: Passed | D3: =COUNTIF(G6:G22,"Pass") -> 0 | E3: Failed | F3: =COUNTIF(G6:G22,"Fail") -> 0 | G3: Blocked | H3: =COUNTIF(G6:G22,"Blocked") -> 0 | I3: Completion | J3: =IF(B3=0,0,(COUNTIF(G6:G22,"Pass")+COUNTIF(G6:G22,"Fail")+COUNTIF(G6:G22,"Blocked")+COUNTIF(G6:G22,"N/A"))/B3) -> 0 | K3: Update Status in column G
A5: Test ID | B5: Priority | C5: Scenario | D5: Preconditions | E5: Test Steps | F5: Expected Outcome | G5: Status | H5: Tester | I5: Test Date | J5: Evidence / Defect Link | K5: Notes
A6: SVC-01 | B6: P1 | C6: Show current model read-only | D6: Organization administrator is signed in. | E6: Open service-model settings. | F6: Current model and effective details are visible but cannot be edited directly. | G6: Not Started
A7: SVC-02 | B7: P0 | C7: Submit service-model request | D7: No active request exists. | E7: Choose a different model, provide reason/effective date, and submit. | F7: A Pending request is created while the current model remains unchanged. | G7: Not Started
A8: SVC-03 | B8: P1 | C8: Notify active platform administrators | D8: Multiple active platform admins exist. | E8: Submit the request. | F8: All active platform admins receive an informative notification/email. | G8: Not Started
A9: SVC-04 | B9: P0 | C9: Reject second active request | D9: A request is already Pending or awaiting organization response. | E9: Submit another request. | F9: The second active request is rejected without overwriting the first. | G9: Not Started
A10: SVC-05 | B10: P0 | C10: Deny request permission | D10: Sign in as a property manager or ordinary user. | E10: Attempt to submit a model-change request. | F10: Access is denied and no request is created. | G10: Not Started
A11: SVC-06 | B11: P1 | C11: Show complete platform review details | D11: Pending request exists. | E11: Open the platform review queue. | F11: Organization, current/requested model, reason, effective date, requester, and history are complete. | G11: Not Started
A12: SVC-07 | B12: P1 | C12: Require note for Request Info | D12: Pending request exists. | E12: Choose Request Info without a note. | F12: Action is rejected and request status remains unchanged. | G12: Not Started
A13: SVC-08 | B13: P0 | C13: Request info with note | D13: Pending request exists. | E13: Provide a note and submit Request Info. | F13: Status changes appropriately and the organization is notified with the note. | G13: Not Started
A14: SVC-09 | B14: P0 | C14: Organization responds to info request | D14: Request is awaiting organization response. | E14: Submit the requested response. | F14: Request returns to platform review and active platform admins are notified. | G14: Not Started
A15: SVC-10 | B15: P1 | C15: Require denial note | D15: Pending request exists. | E15: Choose Deny without a note. | F15: Action is rejected and policy remains unchanged. | G15: Not Started
A16: SVC-11 | B16: P0 | C16: Deny with note | D16: Pending request exists. | E16: Provide a denial note and confirm. | F16: Request is denied, current model remains unchanged, and history/notification include the note. | G16: Not Started
A17: SVC-12 | B17: P0 | C17: Approve request atomically | D17: Pending request matches current policy version. | E17: Approve it. | F17: Model/defaults update, property overrides clear, policy version increments, and status/history/notification update together. | G17: Not Started
... A22: SVC-17 | B22: P1 | C22: Display decision history | D22: Prior approved/denied/request-info decisions exist. | E22: Open service-model history. | F22: Chronological decisions, notes, actors, dates, and versions are visible. | G22: Not Started

Sheet Help Center
A1: Help Center QA | K1: ← QA Summary
A2: Verify audience-specific help content, contextual links, and article completeness.
A3: Total | B3: =COUNTA(A6:A12) -> 7 | C3: Passed | D3: =COUNTIF(G6:G12,"Pass") -> 0 | E3: Failed | F3: =COUNTIF(G6:G12,"Fail") -> 0 | G3: Blocked | H3: =COUNTIF(G6:G12,"Blocked") -> 0 | I3: Completion | J3: =IF(B3=0,0,(COUNTIF(G6:G12,"Pass")+COUNTIF(G6:G12,"Fail")+COUNTIF(G6:G12,"Blocked")+COUNTIF(G6:G12,"N/A"))/B3) -> 0 | K3: Update Status in column G
A5: Test ID | B5: Priority | C5: Scenario | D5: Preconditions | E5: Test Steps | F5: Expected Outcome | G5: Status | H5: Tester | I5: Test Date | J5: Evidence / Defect Link | K5: Notes
A6: HLP-01 | B6: P1 | C6: Open public contractor setup article | D6: Signed out. | E6: Open the public contractor setup help URL. | F6: The intended public article loads without exposing private application data. | G6: Not Started
A7: HLP-02 | B7: P1 | C7: Show contractor guidance | D7: Signed in as a contractor. | E7: Open Help Center. | F7: Resource workflow and earnings/Gusto guides are visible. | G7: Not Started
A8: HLP-03 | B8: P1 | C8: Tailor employee/owner guidance | D8: Signed in as an employee/owner resource. | E8: Open Help Center. | F8: Resource workflow help is visible while contractor earnings guidance is absent. | G8: Not Started
A9: HLP-04 | B9: P1 | C9: Show platform guidance | D9: Signed in as platform administrator. | E9: Open Help Center. | F9: Platform, Gusto, service billing, and review guides are visible. | G9: Not Started
A10: HLP-05 | B10: P1 | C10: Restrict organization-admin help | D10: Signed in as organization administrator. | E10: Open Help Center. | F10: Organization guidance is visible and platform-only operational content is hidden. | G10: Not Started
A11: HLP-06 | B11: P1 | C11: Open contextual help links | D11: Scheduler, Resources, Service Billing, and Service Delivery pages are available. | E11: Open each contextual help link. | F11: Each link lands on the relevant article and preserves a usable return path. | G11: Not Started
A12: HLP-07 | B12: P1 | C12: Load complete article catalog | D12: Help Center is reachable. | E12: Open all 16 articles. | F12: Every article loads with no missing assets, broken navigation, or console errors. | G12: Not Started

Sheet Notifications Email
A1: Notifications Email QA | K1: ← QA Summary
A2: Verify recipient routing and ensure delivery failures never roll back primary business records.
A3: Total | B3: =COUNTA(A6:A11) -> 6 | C3: Passed | D3: =COUNTIF(G6:G11,"Pass") -> 0 | E3: Failed | F3: =COUNTIF(G6:G11,"Fail") -> 0 | G3: Blocked | H3: =COUNTIF(G6:G11,"Blocked") -> 0 | I3: Completion | J3: =IF(B3=0,0,(COUNTIF(G6:G11,"Pass")+COUNTIF(G6:G11,"Fail")+COUNTIF(G6:G11,"Blocked")+COUNTIF(G6:G11,"N/A"))/B3) -> 0 | K3: Update Status in column G
A5: Test ID | B5: Priority | C5: Scenario | D5: Preconditions | E5: Test Steps | F5: Expected Outcome | G5: Status | H5: Tester | I5: Test Date | J5: Evidence / Defect Link | K5: Notes
A6: NTF-01 | B6: P0 | C6: Notify resource without org membership | D6: Resource-only contractor is deployed and assigned. | E6: Create/send the assignment notification. | F6: The resource receives the notification despite having no organization membership. | G6: Not Started
A7: NTF-02 | B7: P0 | C7: Send successful SES attachments | D7: SES is functioning and an inspection/report/invoice is ready. | E7: Complete the workflow and inspect received messages. | F7: Correct recipients receive the expected report and invoice attachments. | G7: Not Started
A8: NTF-03 | B8: P0 | C8: Keep completion after SES failure | D8: SES is intentionally invalid. | E8: Complete an inspection. | F8: Completion and PDFs persist, an error is recorded, and retry does not duplicate artifacts. | G8: Not Started
A9: NTF-04 | B9: P0 | C9: Keep service request after email failure | D9: Service-model email delivery is configured to fail. | E9: Submit or update a service-model request. | F9: The in-app request/history persists and the delivery problem is visible. | G9: Not Started
A10: NTF-05 | B10: P1 | C10: Notify all active platform admins | D10: Multiple active and inactive platform admins exist. | E10: Create/update a service-model request. | F10: All active platform admins are notified; inactive accounts are not treated as recipients. | G10: Not Started
A11: NTF-06 | B11: P0 | C11: Route completion notifications correctly | D11: Contractor assignment exists for Property A. | E11: Complete the inspection. | F11: Notifications reference the correct resource portal, organization, property, and assignment. | G11: Not Started

Sheet Cleanup Smoke
A1: Cleanup Smoke QA | K1: ← QA Summary
A2: Confirm the authentication, route, Mapbox, and dependency cleanup did not remove live behavior.
A3: Total | B3: =COUNTA(A6:A15) -> 10 | C3: Passed | D3: =COUNTIF(G6:G15,"Pass") -> 0 | E3: Failed | F3: =COUNTIF(G6:G15,"Fail") -> 0 | G3: Blocked | H3: =COUNTIF(G6:G15,"Blocked") -> 0 | I3: Completion | J3: =IF(B3=0,0,(COUNTIF(G6:G15,"Pass")+COUNTIF(G6:G15,"Fail")+COUNTIF(G6:G15,"Blocked")+COUNTIF(G6:G15,"N/A"))/B3) -> 0 | K3: Update Status in column G
A5: Test ID | B5: Priority | C5: Scenario | D5: Preconditions | E5: Test Steps | F5: Expected Outcome | G5: Status | H5: Tester | I5: Test Date | J5: Evidence / Defect Link | K5: Notes
A6: CLN-01 | B6: P0 | C6: Use live client assignment route | D6: Authorized user and valid client/property fixtures exist. | E6: Call /api/client/assign-client through the supported UI/API path. | F6: The supported route succeeds with the expected authorization and response. | G6: Not Started
A7: CLN-02 | B7: P0 | C7: Exercise AzRoots property routes | D7: Authorized AzRoots test data exists. | E7: Run the supported property GET and PUT workflows. | F7: Both operations succeed with no authentication regression. | G7: Not Started
A8: CLN-03 | B8: P0 | C8: Load consolidated payments summary | D8: User has submissions, assignments, and mileage/payment history. | E8: Open/call the consolidated payments summary. | F8: Response includes submissions, assignments, current mileage, YTD mileage, and YTD payments. | G8: Not Started
A9: CLN-04 | B9: P0 | C9: Retire admin user-submissions route | D9: Use an authenticated admin request. | E9: Call /admin/user-submissions/:id. | F9: Endpoint returns 404 and no duplicate legacy handler responds. | G9: Not Started
A10: CLN-05 | B10: P0 | C10: Retire admin assign-client route | D10: Use an authenticated admin request. | E10: Call /admin/assign-client-to-property. | F10: Endpoint returns 404; the supported client route remains functional. | G10: Not Started
A11: CLN-06 | B11: P0 | C11: Retire mileage user route | D11: Use an authenticated request. | E11: Call /api/mileage/user/:id. | F11: Endpoint returns 404; consolidated mileage/payment data remains available. | G11: Not Started
A12: CLN-07 | B12: P1 | C12: Remove global Mapbox resources | D12: Browser cache is disabled or cleared. | E12: Load the application and inspect network/document styles. | F12: Global Mapbox GL and Directions CSS resources are absent. | G12: Not Started
A13: CLN-08 | B13: P0 | C13: Preserve geocoding behavior | D13: A workflow using address geocoding is available. | E13: Search/resolve a valid address. | F13: Geocoding still returns and applies the expected result. | G13: Not Started
A14: CLN-09 | B14: P1 | C14: Avoid duplicate authentication work | D14: Client and AzRoots routes are instrumented/logged. | E14: Make one authorized request to each. | F14: Each request completes under one authenticated session with no duplicate authentication errors or repeated side effects. | G14: Not Started
A15: CLN-10 | B15: P0 | C15: Run full navigation smoke | D15: Representative platform, organization, and resource accounts exist. | E15: Exercise login, dashboards, billing, and Help Center. | F15: Core pages load with no new browser console errors or backend exceptions. | G15: Not Started

Sheet Exit Criteria
A1: Exit Criteria QA | K1: ← QA Summary
A2: Release gates that must be satisfied before the DEV change set is promoted.
A3: Total | B3: =COUNTA(A6:A13) -> 8 | C3: Passed | D3: =COUNTIF(G6:G13,"Pass") -> 0 | E3: Failed | F3: =COUNTIF(G6:G13,"Fail") -> 0 | G3: Blocked | H3: =COUNTIF(G6:G13,"Blocked") -> 0 | I3: Completion | J3: =IF(B3=0,0,(COUNTIF(G6:G13,"Pass")+COUNTIF(G6:G13,"Fail")+COUNTIF(G6:G13,"Blocked")+COUNTIF(G6:G13,"N/A"))/B3) -> 0 | K3: Update Status in column G
A5: Test ID | B5: Priority | C5: Scenario | D5: Preconditions | E5: Test Steps | F5: Expected Outcome | G5: Status | H5: Tester | I5: Test Date | J5: Evidence / Defect Link | K5: Notes
A6: EXT-01 | B6: P0 | C6: All P0 cases pass | D6: All module testing is complete. | E6: Review P0 rows across the workbook. | F6: Every applicable P0 row is Pass; any exception is formally accepted and linked. | G6: Not Started
A7: EXT-02 | B7: P0 | C7: No cross-tenant access | D7: Permission and tampering tests are complete. | E7: Review evidence for organization, property, and resource boundaries. | F7: No account accessed another tenant/property/assignment outside its authorization. | G7: Not Started
A8: EXT-03 | B8: P0 | C8: Amounts remain independent | D8: Invoice and earning tests are complete. | E8: Compare contractor compensation and customer billing across workflows. | F8: Contractor amounts and customer invoice amounts never overwrite or derive from one another incorrectly. | G8: Not Started
A9: EXT-04 | B9: P0 | C9: Retries remain idempotent | D9: Retry/failure-path testing is complete. | E9: Review inspection, PDF, invoice, and earning record counts. | F9: No retry created duplicate inspections, PDFs, invoices, or earnings. | G9: Not Started
A10: EXT-05 | B10: P0 | C10: Completed assignments can be scheduled again | D10: Scheduler regression tests are complete. | E10: Review completed-combination reuse evidence. | F10: A new assignment can reuse a previously completed resource/property/date combination. | G10: Not Started
A11: EXT-06 | B11: P0 | C11: Service policy changes are future-only | D11: Service-model approval tests are complete. | E11: Compare pre- and post-approval records. | F11: Historical assignments/invoices remain unchanged and only new work uses the new policy. | G11: Not Started
A12: EXT-07 | B12: P0 | C12: Email failures are non-destructive | D12: SES failure tests are complete. | E12: Review primary records and delivery errors. | F12: Business records persist and failures are observable/retryable without duplication. | G12: Not Started
A13: EXT-08 | B13: P0 | C13: No new uncaught errors | D13: Full smoke and targeted tests are complete. | E13: Review browser console and backend logs. | F13: No new uncaught frontend errors, unhandled promise rejections, or backend exceptions remain. | G13: Not Started
